pyrda/__init__.py
pyrda/main.py
pyrda/sqlserver.py
pyrda/dbms/__init__.py
pyrda/dbms/config.py
pyrda/dbms/mssql.py
pyrda/dbms/mysql.py
pyrda/dbms/oracle.py
pyrda/dbms/rds.py
pyrda/dbms/sqlite..py
pyrda/nosql/__init__.py
pyrda-1.8.4.dist-info/LICENSE
pyrda-1.8.4.dist-info/METADATA
pyrda-1.8.4.dist-info/WHEEL
pyrda-1.8.4.dist-info/top_level.txt
pyrda-1.8.4.dist-info/RECORD
