Metadata-Version: 2.1
Name: pyrda
Version: 1.8.4
Summary: reshape data access in py language 
Home-page: http://www.reshapedata.com
Author: Reshapedata
Author-email: hulilei@takewiki.com.cn
License: Apache License
Keywords: reshapedata,rda,pyrda
Platform: UNKNOWN
Requires-Python: >=3.6
License-File: LICENSE
Requires-Dist: pymssql
